anyboxes/__init__.py
anyboxes/_errors.py
anyboxes/_version.py
anyboxes/py.typed
anyboxes/implementations/__init__.py
anyboxes/implementations/origin.py
anyboxes/implementations/torch/__init__.py
anyboxes/implementations/torch/_typing.py
anyboxes/implementations/torch/boxes.py
anyboxes/implementations/torch/coordinates.py
anyboxes-0.1.1.dist-info/LICENSE
anyboxes-0.1.1.dist-info/METADATA
anyboxes-0.1.1.dist-info/WHEEL
anyboxes-0.1.1.dist-info/top_level.txt
anyboxes-0.1.1.dist-info/RECORD
