Metadata-Version: 2.1
Name: anyboxes
Version: 0.1.1
Summary: Lightweight package for managing bounding boxes that works seamlessly with most computing frameworks.
Author-email: Vincent Duchauffour <vincent.duchauffour@proton.me>
License: MIT License
Project-URL: Homepage, https://github.com/VDuchauffour/anyboxes
Project-URL: Source, https://github.com/VDuchauffour/anyboxes
Project-URL: Tracker, https://github.com/VDuchauffour/anyboxes/issues
Keywords: computer vision,machine learning,bounding boxes
Classifier: License :: OSI Approved :: MIT License
Classifier: Operating System :: OS Independent
Classifier: Programming Language :: Python
Classifier: Programming Language :: Python :: 3.8
Classifier: Programming Language :: Python :: 3.9
Classifier: Programming Language :: Python :: 3.10
Classifier: Programming Language :: Python :: 3.11
Classifier: Intended Audience :: Developers
Classifier: Topic :: Scientific/Engineering :: Artificial Intelligence
Classifier: Framework :: Pytest
Requires-Python: >=3.8
License-File: LICENSE
Requires-Dist: numpy (>=1.21)
Provides-Extra: all
Requires-Dist: anyboxes[torch] ; extra == 'all'
Requires-Dist: anyboxes[jax] ; extra == 'all'
Requires-Dist: anyboxes[tensorflow] ; extra == 'all'
Provides-Extra: dev
Requires-Dist: pre-commit ; extra == 'dev'
Requires-Dist: black ; extra == 'dev'
Requires-Dist: isort ; extra == 'dev'
Requires-Dist: ruff ; extra == 'dev'
Requires-Dist: mypy ; extra == 'dev'
Requires-Dist: pyright ; extra == 'dev'
Requires-Dist: docformatter ; extra == 'dev'
Requires-Dist: interrogate ; extra == 'dev'
Requires-Dist: pytest ; extra == 'dev'
Requires-Dist: pytest-cov ; extra == 'dev'
Provides-Extra: jax
Requires-Dist: jax ; extra == 'jax'
Provides-Extra: tensorflow
Requires-Dist: tensorflow ; extra == 'tensorflow'
Provides-Extra: torch
Requires-Dist: torch ; extra == 'torch'
